{"articles_and_essays":null,
"cite_this":{
    "apa": "Fenzi, J. &amp; Kidder, D. R. (1998) <cite>Interview with Dorothy Robinson Kidder</cite>. June 1. [Manuscript/Mixed Material] Retrieved from the Library of Congress, https://www.loc.gov/item/mfdipbib000609/.", 
    "mla": "Fenzi, Jewell, and Dorothy Robinson Kidder. <cite>Interview with Dorothy Robinson Kidder</cite>. June 1, 1998. Manuscript/Mixed Material. Retrieved from the Library of Congress, &lt;https://www.loc.gov/item/mfdipbib000609/&gt;.", 
    "chicago": "Fenzi, Jewell, and Dorothy Robinson Kidder. <cite>Interview with Dorothy Robinson Kidder</cite>. June 1, 1998. Manuscript/Mixed Material. Retrieved from the Library of Congress, https://www.loc.gov/item/mfdipbib000609/. (Accessed February 06, 2017.)"
},
"timestamp":1486412190326,
"locations":[
    [
        {
            "geometry": {
                "type": "Point", 
                "coordinates": [
                    2.3213888888888885, 
                    48.843055555555559
                ]
            }, 
            "type": "Feature", 
            "properties": {
                "is_composite": null, 
                "name": "Montparnasse (Paris, France)", 
                "area": null, 
                "importance": null, 
                "is_primary": true, 
                "alternate": [
                    {
                        "name": "Quartier du Montparnasse (Paris, France)"
                    }, 
                    {
                        "type": "historical", 
                        "name": "Paris. Montparnasse"
                    }
                ], 
                "uris": [
                    "http://id.loc.gov/authorities/names/n82144259"
                ], 
                "admin": [
                    {
                        "feature_code": "ADM0", 
                        "alternate_names": "Fr. FRA French Republic", 
                        "id": "83c7499f1fd87361", 
                        "name": "France"
                    }, 
                    {
                        "feature_code": "ADM1", 
                        "alternate_names": "", 
                        "id": "c2630b5cd7ca7888", 
                        "name": "\u00cele-de-France"
                    }
                ], 
                "feature_code": "PPL", 
                "feature_code_name": "populated place", 
                "timeframe": {}, 
                "id": "b2042e1effd4d1cc", 
                "population": null
            }
        }
    ], 
    [
        {
            "geometry": {
                "type": "Point", 
                "coordinates": [
                    -41.850000000000001, 
                    -22.383333333333333
                ]
            }, 
            "type": "Feature", 
            "properties": {
                "is_composite": null, 
                "name": "Santa Teresa (Rio de Janeiro, Brazil)", 
                "area": null, 
                "importance": null, 
                "is_primary": true, 
                "alternate": [
                    {
                        "name": "Santa Tereza (Rio de Janeiro, Brazil)"
                    }
                ], 
                "uris": [
                    "http://id.loc.gov/authorities/names/n89242073"
                ], 
                "admin": [
                    {
                        "feature_code": "ADM0", 
                        "alternate_names": "Brazil BRA Federative Republic of Brazil", 
                        "id": "3556e87fc8d3b35a", 
                        "name": "Brazil"
                    }, 
                    {
                        "feature_code": "ADM1", 
                        "alternate_names": "Rio", 
                        "id": "48567189b8fac4f1", 
                        "name": "Rio de Janeiro"
                    }
                ], 
                "feature_code": "PPL", 
                "feature_code_name": "populated place", 
                "timeframe": {}, 
                "id": "5861c36637cea175", 
                "population": null
            }
        }
    ], 
    [
        {
            "geometry": {
                "type": "Point", 
                "coordinates": [
                    100.494086, 
                    13.7527531
                ]
            }, 
            "type": "Feature", 
            "properties": {
                "is_composite": null, 
                "name": "Bangkok", 
                "area": null, 
                "importance": null, 
                "is_primary": true, 
                "alternate": [
                    {
                        "lang": "unknown", 
                        "name": "\u0e01\u0e23\u0e38\u0e07\u0e40\u0e17\u0e1e\u0e21\u0e2b\u0e32\u0e19\u0e04\u0e23 (Bangkok)"
                    }, 
                    {
                        "lang": "cs", 
                        "name": "Bangkok"
                    }, 
                    {
                        "lang": "de", 
                        "name": "Bangkok"
                    }, 
                    {
                        "lang": "en", 
                        "name": "Bangkok"
                    }, 
                    {
                        "lang": "es", 
                        "name": "Bangkok"
                    }, 
                    {
                        "lang": "eu", 
                        "name": "Bangkok"
                    }, 
                    {
                        "lang": "fi", 
                        "name": "Bangkok"
                    }, 
                    {
                        "lang": "fr", 
                        "name": "Bangkok"
                    }, 
                    {
                        "lang": "he", 
                        "name": "\u05d1\u05e0\u05d2\u05e7\u05d5\u05e7"
                    }, 
                    {
                        "lang": "hr", 
                        "name": "Bangkok"
                    }, 
                    {
                        "lang": "is", 
                        "name": "Bangkok"
                    }, 
                    {
                        "lang": "ku", 
                        "name": "Bangkok"
                    }, 
                    {
                        "lang": "pt", 
                        "name": "Bangkok"
                    }, 
                    {
                        "lang": "ru", 
                        "name": "\u0411\u0430\u043d\u0433\u043a\u043e\u043a"
                    }, 
                    {
                        "lang": "sk", 
                        "name": "Bangkok"
                    }, 
                    {
                        "lang": "sl", 
                        "name": "Bangkok"
                    }, 
                    {
                        "lang": "sv", 
                        "name": "Bangkok"
                    }, 
                    {
                        "lang": "th", 
                        "name": "\u0e01\u0e23\u0e38\u0e07\u0e40\u0e17\u0e1e\u0e21\u0e2b\u0e32\u0e19\u0e04\u0e23"
                    }, 
                    {
                        "lang": "vi", 
                        "name": "B\u0103ng C\u1ed1c"
                    }
                ], 
                "uris": [
                    "osm.org/browse/node/1628207792"
                ], 
                "admin": [
                    {
                        "feature_code": "ADM1", 
                        "alternate_names": "Bangkok|Krung Thep|Krung Thep Maha Nakhon|Phra Nakhon-Thonburi", 
                        "id": "90204ebf0920e145", 
                        "name": "Bangkok Metropolis"
                    }, 
                    {
                        "feature_code": "ADM0", 
                        "alternate_names": "Thai. THA Kingdom of Thailand", 
                        "id": "5f44bdb574c836ec", 
                        "name": "Thailand"
                    }
                ], 
                "feature_code": "PPL", 
                "feature_code_name": "populated place", 
                "timeframe": {}, 
                "id": "16a57d31ba2dadfe", 
                "population": null
            }
        }
    ], 
    [
        {
            "geometry": {
                "type": "Point", 
                "coordinates": [
                    151.2164539, 
                    -33.854815700000003
                ]
            }, 
            "type": "Feature", 
            "properties": {
                "is_composite": null, 
                "name": "Sydney", 
                "area": null, 
                "importance": null, 
                "is_primary": true, 
                "alternate": [
                    {
                        "lang": "es", 
                        "name": "S\u00eddney"
                    }, 
                    {
                        "lang": "fr", 
                        "name": "Sydney"
                    }, 
                    {
                        "lang": "he", 
                        "name": "\u05e1\u05d9\u05d3\u05e0\u05d9"
                    }, 
                    {
                        "lang": "is", 
                        "name": "Sydney"
                    }, 
                    {
                        "lang": "pl", 
                        "name": "Sydney"
                    }, 
                    {
                        "lang": "ru", 
                        "name": "\u0421\u0438\u0434\u043d\u0435\u0439"
                    }, 
                    {
                        "lang": "sv", 
                        "name": "Sydney"
                    }
                ], 
                "uris": [
                    "osm.org/browse/node/13766899"
                ], 
                "admin": [
                    {
                        "feature_code": "ADM1", 
                        "alternate_names": "N.S.W.", 
                        "id": "6882278046168f86", 
                        "name": "New South Wales"
                    }, 
                    {
                        "feature_code": "ADM0", 
                        "alternate_names": "Auz. AUS Commonwealth of Australia", 
                        "id": "870b586c4b2dec11", 
                        "name": "Australia"
                    }
                ], 
                "feature_code": "PPL", 
                "feature_code_name": "populated place", 
                "timeframe": {}, 
                "id": "fc661fd6c0b2eb40", 
                "population": null
            }
        }
    ]
],
"related_items":[
    {
        "access_restricted": true, 
        "original_format": [
            "photo, print, drawing"
        ], 
        "latlong": "45.452853,-73.6442548", 
        "id": "http://www.loc.gov/item/2011648257/", 
        "partof": [
            "prints and photographs division", 
            "catalog"
        ], 
        "subject": [
            "expo (international exhibitions bureau)", 
            "(", 
            "montr\u00e9al, qu\u00e9bec)", 
            "exhibitions", 
            "canada", 
            "montreal", 
            "exhibition buildings", 
            "hammer & sickle", 
            "photographic prints"
        ], 
        "index": 1, 
        "group": [
            "cph", 
            "catalog", 
            "miscellaneous-items-high-demand"
        ], 
        "title": "Soviet and U.S. exhibits", 
        "coordinates": [
            "45.452853,-73.6442548"
        ], 
        "online_format": [
            "image"
        ], 
        "score": 0.31639874000000001, 
        "lonlat": [
            -73.644254799999999, 
            45.452852999999998
        ], 
        "location": [
            "canada", 
            "qu\u00e9bec", 
            "montr\u00e9al", 
            "montreal"
        ], 
        "mime_type": [
            "image/gif", 
            "image/jpg", 
            "image/tif", 
            "image/jpeg"
        ], 
        "digitized": true, 
        "description": [
            "1 photographic print."
        ], 
        "timestamp": "2016-07-20T00:07:17.259000Z", 
        "site": [
            "pictures", 
            "catalog"
        ], 
        "campaigns": [], 
        "extract_timestamp": "2016-05-16T14:01:14.463000Z", 
        "date": "1967", 
        "shelf_id": "NYWTS - SUBJ/GEOG--Expositions--World's fair--Montreal--1967 [item] [P&P]", 
        "other_title": [], 
        "dates": [
            "1967-01-01T00:00:00Z"
        ], 
        "language": [
            "english"
        ], 
        "url": "https://www.loc.gov/item/2011648257/", 
        "hassegments": false, 
        "image_url": [
            "//cdn.loc.gov/service/pnp/ds/00600/00604_150px.jpg"
        ], 
        "aka": [
            "http://www.loc.gov/pictures/collection/cph/item/2011648257/", 
            "http://www.loc.gov/item/2011648257/", 
            "http://www.loc.gov/pictures/item/2011648257/", 
            "http://hdl.loc.gov/loc.pnp/ds.00604", 
            "http://www.loc.gov/resource/ds.00604/", 
            "http://lccn.loc.gov/2011648257"
        ]
    }, 
    {
        "access_restricted": false, 
        "original_format": [
            "photo, print, drawing"
        ], 
        "contributor": [
            "detroit photographic co."
        ], 
        "id": "http://www.loc.gov/item/2008679504/", 
        "partof": [
            "prints and photographs division", 
            "photochrom prints", 
            "lot 13923", 
            "catalog"
        ], 
        "subject": [
            "maisonneuve, paul de chomedey de", 
            "statues", 
            "sculpture", 
            "canada", 
            "quebec (province)", 
            "montreal", 
            "photochrom prints", 
            "color", 
            "qu\u00e9bec (province)", 
            "montr\u00e9al"
        ], 
        "index": 2, 
        "group": [
            "pgz", 
            "catalog", 
            "photochrom"
        ], 
        "title": "Statue of Maisonneuve, Montreal", 
        "online_format": [
            "image"
        ], 
        "score": 0.30723840000000002, 
        "location": [
            "canada", 
            "quebec", 
            "montreal", 
            "qu\u00e9bec", 
            "montr\u00e9al"
        ], 
        "mime_type": [
            "image/gif", 
            "image/jpg", 
            "image/tif", 
            "image/jpeg"
        ], 
        "digitized": true, 
        "description": [
            "1 photomechanical print : photochrom, color. | Print shows statue of Paul de Chomedey de Maisonneuve (1612-1676), a French military officer and founder of Montreal, located at Place d'Armes Square, Montreal. (Source: Flickr Commons project, 2009)."
        ], 
        "timestamp": "2016-07-15T21:09:13.292000Z", 
        "site": [
            "pictures", 
            "catalog"
        ], 
        "campaigns": [], 
        "extract_timestamp": "2016-07-15T20:54:27.458000Z", 
        "date": "1901", 
        "shelf_id": "LOT 13923, no. 296 [item] [P&P]", 
        "other_title": [], 
        "dates": [
            "1901-01-01T00:00:00Z"
        ], 
        "language": [
            "english"
        ], 
        "url": "https://www.loc.gov/item/2008679504/", 
        "hassegments": false, 
        "image_url": [
            "//cdn.loc.gov/service/pnp/ppmsca/18100/18104_150px.jpg", 
            "//cdn.loc.gov/service/pnp/ppmsca/18100/18104_150px.jpg#h=150&w=118", 
            "//cdn.loc.gov/service/pnp/ppmsca/18100/18104t.gif#h=150&w=118", 
            "//cdn.loc.gov/service/pnp/ppmsca/18100/18104r.jpg#h=640&w=502", 
            "//cdn.loc.gov/service/pnp/ppmsca/18100/18104v.jpg#h=1024&w=803"
        ], 
        "aka": [
            "http://www.loc.gov/pictures/collection/pgz/item/2008679504/", 
            "http://www.loc.gov/item/2008679504/", 
            "http://www.loc.gov/pictures/item/2008679504/", 
            "http://hdl.loc.gov/loc.pnp/ppmsca.18104", 
            "http://www.loc.gov/resource/ppmsca.18104/", 
            "http://lccn.loc.gov/2008679504"
        ]
    }, 
    {
        "access_restricted": false, 
        "original_format": [
            "film, video"
        ], 
        "latlong": "45.0210653,-72.3520485", 
        "contributor": [
            "thomas a. edison, inc", 
            "paper print collection (library of congress)", 
            "niver (kemp) collection (library of congress)"
        ], 
        "id": "http://www.loc.gov/item/00694190/", 
        "partof": [
            "motion picture, broadcasting and recorded sound division", 
            "inventing entertainment: the early motion pictures and sound recordings of the edison companies", 
            "american memory", 
            "catalog"
        ], 
        "subject": [
            "george", 
            "v", 
            "king of great britain", 
            "travel", 
            "qu\u00e9bec (province)", 
            "great britain", 
            "kings and rulers", 
            "bridges", 
            "quebec (province)", 
            "montreal", 
            "dedication services", 
            "soldiers", 
            "canada", 
            "officials and employees", 
            "montreal (quebec)", 
            "description and travel", 
            "actualities (motion pictures)", 
            "mary", 
            "queen, consort of george v, king of great britain", 
            "pont victoria (montr\u00e9al, qu\u00e9bec)", 
            "silent films", 
            "short films", 
            "nonfiction films"
        ], 
        "index": 3, 
        "group": [
            "papr.mar", 
            "catalog", 
            "edison-companies-motion-pictures-and-sound-recordings"
        ], 
        "title": "Duke of York at Montreal and Quebec", 
        "coordinates": [
            "45.0210653,-72.3520485"
        ], 
        "online_format": [
            "image", 
            "video"
        ], 
        "score": 0.2633472, 
        "lonlat": [
            -72.352048499999995, 
            45.021065299999997
        ], 
        "location": [
            "canada", 
            "qu\u00e9bec", 
            "great britain", 
            "quebec", 
            "montreal", 
            "montr\u00e9al", 
            "pont victoria"
        ], 
        "mime_type": [
            "image/gif", 
            "video/mov", 
            "video/mpeg", 
            "application/x-video", 
            "image/jpeg"
        ], 
        "digitized": true, 
        "description": [
            "From K. Niver: This film shows the citation, presentation, and dedication of a bridge by the Duke of York, later King of England and grandfather of Queen Elizabeth. Many high-ranking military officials of both England and Canada are with him."
        ], 
        "timestamp": "2016-11-25T21:36:04.763000Z", 
        "site": [
            "ammem", 
            "catalog"
        ], 
        "campaigns": [], 
        "extract_timestamp": "2016-11-25T21:34:51.111000Z", 
        "date": "1901", 
        "shelf_id": "FEC 2275 (ref print) LC 1999 (paper pos)", 
        "other_title": [], 
        "dates": [
            "1901-01-01T00:00:00Z"
        ], 
        "language": [
            "english"
        ], 
        "url": "https://www.loc.gov/item/00694190/", 
        "hassegments": false, 
        "image_url": [
            "//lcweb2.loc.gov/mbrs/edmp/1999t.gif"
        ], 
        "aka": [
            "http://hdl.loc.gov/loc.mbrsmi/edmp.1999", 
            "http://www.loc.gov/item/00694190/", 
            "http://www.loc.gov/resource/edmp.1999/", 
            "http://lccn.loc.gov/00694190"
        ]
    }, 
    {
        "access_restricted": false, 
        "site": [
            "pictures"
        ], 
        "original_format": [
            "photo, print, drawing"
        ], 
        "contributor": [
            "detroit publishing co."
        ], 
        "id": "http://www.loc.gov/item/det1994022517/PP/", 
        "partof": [
            "prints and photographs division", 
            "detroit publishing company", 
            "american memory"
        ], 
        "subject": [
            "galleries & museums", 
            "canada", 
            "quebec (province)", 
            "montreal", 
            "dry plate negatives", 
            "reproductions"
        ], 
        "index": 4, 
        "group": [
            "det", 
            "detroit-publishing-company"
        ], 
        "title": "Chateau de Ramezay, Montreal", 
        "online_format": [
            "image"
        ], 
        "score": 0.26309090000000002, 
        "location": [
            "canada", 
            "quebec", 
            "montreal"
        ], 
        "mime_type": [
            "image/gif", 
            "image/jpg", 
            "image/tif"
        ], 
        "digitized": true, 
        "description": [
            "1 negative : glass ; 8 x 10 in."
        ], 
        "timestamp": "2016-05-26T15:58:19.256000Z", 
        "campaigns": [], 
        "extract_timestamp": "2016-05-26T15:12:56.347000Z", 
        "date": "1900", 
        "shelf_id": "LC-D414-K3484 <P&P> [P&P]", 
        "other_title": [], 
        "dates": [
            "1900-01-01T00:00:00Z"
        ], 
        "language": [
            "english"
        ], 
        "url": "https://www.loc.gov/item/det1994022517/PP/", 
        "hassegments": false, 
        "image_url": [
            "//cdn.loc.gov/service/pnp/det/4a20000/4a25000/4a25900/4a25921_150px.jpg#h=120&w=150", 
            "//cdn.loc.gov/service/pnp/det/4a20000/4a25000/4a25900/4a25921t.gif#h=120&w=150", 
            "//cdn.loc.gov/service/pnp/det/4a20000/4a25000/4a25900/4a25921r.jpg#h=511&w=640", 
            "//cdn.loc.gov/service/pnp/det/4a20000/4a25000/4a25900/4a25921v.jpg#h=818&w=1024"
        ], 
        "aka": [
            "http://www.loc.gov/pictures/collection/det/item/det1994022517/pp/", 
            "http://www.loc.gov/item/det1994022517/pp/", 
            "http://www.loc.gov/pictures/item/det1994022517/pp/", 
            "http://hdl.loc.gov/loc.pnp/det.4a25921", 
            "http://www.loc.gov/resource/det.4a25921/"
        ]
    }, 
    {
        "access_restricted": false, 
        "site": [
            "pictures"
        ], 
        "original_format": [
            "photo, print, drawing"
        ], 
        "contributor": [
            "detroit publishing co."
        ], 
        "id": "http://www.loc.gov/item/det1994025123/PP/", 
        "partof": [
            "prints and photographs division", 
            "detroit publishing company", 
            "american memory"
        ], 
        "subject": [
            "plazas", 
            "canada", 
            "quebec (province)", 
            "montreal", 
            "cityscape photographs", 
            "glass negatives", 
            "mammoth plates"
        ], 
        "index": 5, 
        "group": [
            "det", 
            "detroit-publishing-company"
        ], 
        "title": "Montreal from the Church of Notre Dame", 
        "online_format": [
            "image"
        ], 
        "score": 0.26309090000000002, 
        "location": [
            "canada", 
            "quebec", 
            "montreal"
        ], 
        "mime_type": [
            "image/gif", 
            "image/jpg", 
            "image/tif"
        ], 
        "digitized": true, 
        "description": [
            "1 negative : glass ; 18 x 22 in."
        ], 
        "timestamp": "2016-05-26T16:03:19.057000Z", 
        "campaigns": [], 
        "extract_timestamp": "2016-05-26T15:13:09.381000Z", 
        "date": "1901", 
        "shelf_id": "LC-D43-15096 <P&P> [P&P]", 
        "other_title": [], 
        "dates": [
            "1901-01-01T00:00:00Z"
        ], 
        "language": [
            "english"
        ], 
        "url": "https://www.loc.gov/item/det1994025123/PP/", 
        "hassegments": false, 
        "image_url": [
            "//cdn.loc.gov/service/pnp/det/4a30000/4a33000/4a33000/4a33068_150px.jpg#h=121&w=150", 
            "//cdn.loc.gov/service/pnp/det/4a30000/4a33000/4a33000/4a33068t.gif#h=121&w=150", 
            "//cdn.loc.gov/service/pnp/det/4a30000/4a33000/4a33000/4a33068r.jpg#h=420&w=522", 
            "//cdn.loc.gov/service/pnp/det/4a30000/4a33000/4a33000/4a33068v.jpg#h=824&w=1024"
        ], 
        "aka": [
            "http://www.loc.gov/pictures/collection/det/item/det1994025123/pp/", 
            "http://www.loc.gov/item/det1994025123/pp/", 
            "http://www.loc.gov/pictures/item/det1994025123/pp/", 
            "http://hdl.loc.gov/loc.pnp/det.4a33068", 
            "http://www.loc.gov/resource/det.4a33068/"
        ]
    }, 
    {
        "access_restricted": false, 
        "site": [
            "pictures"
        ], 
        "original_format": [
            "photo, print, drawing"
        ], 
        "contributor": [
            "detroit publishing co."
        ], 
        "id": "http://www.loc.gov/item/det1994025212/PP/", 
        "partof": [
            "prints and photographs division", 
            "detroit publishing company", 
            "american memory"
        ], 
        "subject": [
            "canada", 
            "quebec (province)", 
            "montreal", 
            "cityscape photographs", 
            "glass negatives", 
            "mammoth plates", 
            "panoramic photographs"
        ], 
        "index": 6, 
        "group": [
            "det", 
            "detroit-publishing-company"
        ], 
        "title": "Montreal from Mount Royal", 
        "online_format": [
            "image"
        ], 
        "score": 0.26309090000000002, 
        "location": [
            "canada", 
            "quebec", 
            "montreal"
        ], 
        "mime_type": [
            "image/gif", 
            "image/jpg", 
            "image/tif"
        ], 
        "digitized": true, 
        "description": [
            "2 negatives : glass ; 18 x 22 in."
        ], 
        "timestamp": "2016-05-26T16:03:19.057000Z", 
        "campaigns": [], 
        "extract_timestamp": "2016-05-26T15:13:09.381000Z", 
        "date": "1900", 
        "shelf_id": "LC-D43-37605 <P&P> [P&P]", 
        "other_title": [], 
        "dates": [
            "1900-01-01T00:00:00Z"
        ], 
        "language": [
            "english"
        ], 
        "url": "https://www.loc.gov/item/det1994025212/PP/", 
        "hassegments": false, 
        "image_url": [
            "//cdn.loc.gov/service/pnp/det/4a30000/4a33000/4a33100/4a33134_150px.jpg#h=121&w=150", 
            "//cdn.loc.gov/service/pnp/det/4a30000/4a33000/4a33100/4a33134t.gif#h=121&w=150", 
            "//cdn.loc.gov/service/pnp/det/4a30000/4a33000/4a33100/4a33134r.jpg#h=420&w=519", 
            "//cdn.loc.gov/service/pnp/det/4a30000/4a33000/4a33100/4a33134v.jpg#h=829&w=1024"
        ], 
        "aka": [
            "http://www.loc.gov/pictures/collection/det/item/det1994025212/pp/", 
            "http://www.loc.gov/item/det1994025212/pp/", 
            "http://www.loc.gov/pictures/item/det1994025212/pp/", 
            "http://hdl.loc.gov/loc.pnp/det.4a33135", 
            "http://www.loc.gov/resource/det.4a33134/", 
            "http://www.loc.gov/resource/det.4a33135/"
        ]
    }
],
"more_like_this":[
    {
        "access_restricted": false, 
        "original_format": [
            "manuscript/mixed material"
        ], 
        "contributor": [
            "fenzi, jewell", 
            "mendenhall, leone r. (nonie)"
        ], 
        "latlong": "46.5166666667,31.1216666667", 
        "id": "http://www.loc.gov/item/mfdipbib000808/", 
        "partof": [
            "manuscript division", 
            "frontline diplomacy: the foreign affairs oral history collection of the association for diplomatic studies and training", 
            "american memory"
        ], 
        "subject": [
            "association for diplomatic studies and training", 
            "diplomacy", 
            "foreign relations", 
            "oral history", 
            "spouses", 
            "interviews"
        ], 
        "index": 1, 
        "group": [
            "mfdip", 
            "foreign-affairs-oral-history"
        ], 
        "title": "Interview with Leone R. (Nonie) Mendenhall", 
        "coordinates": [
            "46.5166666667,31.1216666667"
        ], 
        "score": 4.2047889999999999, 
        "lonlat": [
            31.121666666700001, 
            46.516666666699997
        ], 
        "location": [
            "turkey", 
            "saigon", 
            "vientiane", 
            "east asia", 
            "istanbul", 
            "eurasia", 
            "iceland", 
            "europe", 
            "virginia", 
            "pacific", 
            "united states", 
            "vietnam", 
            "western hemisphere", 
            "laos", 
            "switzerland"
        ], 
        "digitized": true, 
        "timestamp": "2016-07-20T18:32:05.602000Z", 
        "campaigns": [], 
        "extract_timestamp": "2016-07-20T18:27:27.142000Z", 
        "date": "1994-04-19", 
        "shelf_id": "Spouse Series", 
        "other_title": [], 
        "dates": [
            "1994-04-19T00:00:00Z"
        ], 
        "language": [
            "english"
        ], 
        "url": "https://www.loc.gov/item/mfdipbib000808/", 
        "hassegments": false, 
        "image_url": [], 
        "aka": [
            "http://www.loc.gov/item/mfdipbib000808/", 
            "http://hdl.loc.gov/loc.mss/mfdip.2004men03", 
            "http://www.loc.gov/resource/mfdip.2004men03/", 
            "http://www.loc.gov/item/mfdip.2004men03/"
        ]
    }, 
    {
        "access_restricted": false, 
        "original_format": [
            "manuscript/mixed material"
        ], 
        "contributor": [
            "fenzi, jewell", 
            "mathews, naomi"
        ], 
        "latlong": "6.66667,-9.66667", 
        "id": "http://www.loc.gov/item/mfdipbib000764/", 
        "partof": [
            "manuscript division", 
            "frontline diplomacy: the foreign affairs oral history collection of the association for diplomatic studies and training", 
            "american memory"
        ], 
        "subject": [
            "association for diplomatic studies and training", 
            "diplomacy", 
            "foreign relations", 
            "oral history", 
            "spouses", 
            "interviews"
        ], 
        "index": 2, 
        "group": [
            "mfdip", 
            "foreign-affairs-oral-history"
        ], 
        "title": "Interview with Naomi Mathews", 
        "coordinates": [
            "6.66667,-9.66667"
        ], 
        "score": 4.175052, 
        "lonlat": [
            -9.6666699999999999, 
            6.6666699999999999
        ], 
        "location": [
            "europe", 
            "eurasia", 
            "india", 
            "pacific", 
            "united states", 
            "lagos", 
            "london", 
            "central asia", 
            "nicaragua", 
            "turkey", 
            "afghanistan", 
            "istanbul", 
            "monrovia", 
            "oslo", 
            "united kingdom", 
            "kabul", 
            "vancouver", 
            "british columbia", 
            "nigeria", 
            "norway", 
            "washington d.c.", 
            "canada", 
            "australia", 
            "sydney", 
            "africa", 
            "liberia", 
            "east asia", 
            "managua", 
            "western hemisphere", 
            "calcutta"
        ], 
        "digitized": true, 
        "timestamp": "2016-07-20T18:31:43.242000Z", 
        "campaigns": [], 
        "extract_timestamp": "2016-07-20T18:27:24.639000Z", 
        "date": "1986-03-20", 
        "shelf_id": "Spouse Series", 
        "other_title": [], 
        "dates": [
            "1986-03-20T00:00:00Z"
        ], 
        "language": [
            "english"
        ], 
        "url": "https://www.loc.gov/item/mfdipbib000764/", 
        "hassegments": false, 
        "image_url": [], 
        "aka": [
            "http://www.loc.gov/item/mfdipbib000764/", 
            "http://hdl.loc.gov/loc.mss/mfdip.2004mat02", 
            "http://www.loc.gov/resource/mfdip.2004mat02/", 
            "http://www.loc.gov/item/mfdip.2004mat02/"
        ]
    }, 
    {
        "access_restricted": false, 
        "original_format": [
            "manuscript/mixed material"
        ], 
        "contributor": [
            "wong, monique", 
            "silberstein, fanchon"
        ], 
        "latlong": "38.9001118,-77.0163653", 
        "id": "http://www.loc.gov/item/mfdipbib001062/", 
        "partof": [
            "manuscript division", 
            "frontline diplomacy: the foreign affairs oral history collection of the association for diplomatic studies and training", 
            "american memory"
        ], 
        "subject": [
            "association for diplomatic studies and training", 
            "diplomacy", 
            "foreign relations", 
            "oral history", 
            "spouses", 
            "interviews"
        ], 
        "index": 3, 
        "group": [
            "mfdip", 
            "foreign-affairs-oral-history"
        ], 
        "title": "Interview with Fanchon Silberstein", 
        "coordinates": [
            "38.9001118,-77.0163653"
        ], 
        "score": 4.0099106000000004, 
        "lonlat": [
            -77.016365300000004, 
            38.900111799999998
        ], 
        "location": [
            "washington d.c.", 
            "saigon", 
            "bangkok", 
            "east asia", 
            "pakistan", 
            "islamabad", 
            "brazil", 
            "washington", 
            "rio de janeiro", 
            "cambodia", 
            "phnom penh", 
            "united states", 
            "central asia", 
            "vietnam", 
            "western hemisphere", 
            "pacific", 
            "laos", 
            "thailand", 
            "saranakhet"
        ], 
        "digitized": true, 
        "timestamp": "2016-07-20T18:32:46.263000Z", 
        "campaigns": [], 
        "extract_timestamp": "2016-07-20T18:27:31.317000Z", 
        "date": "1992-12-09", 
        "shelf_id": "Spouse Series", 
        "other_title": [], 
        "dates": [
            "1992-12-09T00:00:00Z"
        ], 
        "language": [
            "english"
        ], 
        "url": "https://www.loc.gov/item/mfdipbib001062/", 
        "hassegments": false, 
        "image_url": [], 
        "aka": [
            "http://www.loc.gov/item/mfdipbib001062/", 
            "http://hdl.loc.gov/loc.mss/mfdip.2004sil02", 
            "http://www.loc.gov/resource/mfdip.2004sil02/", 
            "http://www.loc.gov/item/mfdip.2004sil02/"
        ]
    }, 
    {
        "access_restricted": false, 
        "original_format": [
            "manuscript/mixed material"
        ], 
        "contributor": [
            "fenzi, jewell", 
            "squire, patricia cody", 
            "lee, eleanore cobb"
        ], 
        "latlong": "38.9256724,-77.0294287", 
        "id": "http://www.loc.gov/item/mfdipbib000673/", 
        "partof": [
            "manuscript division", 
            "frontline diplomacy: the foreign affairs oral history collection of the association for diplomatic studies and training", 
            "american memory"
        ], 
        "subject": [
            "association for diplomatic studies and training", 
            "diplomacy", 
            "foreign relations", 
            "oral history", 
            "spouses", 
            "interviews"
        ], 
        "index": 4, 
        "group": [
            "mfdip", 
            "foreign-affairs-oral-history"
        ], 
        "title": "Interview with Eleanore Cobb Lee", 
        "coordinates": [
            "38.9256724,-77.0294287"
        ], 
        "score": 3.6504629999999998, 
        "lonlat": [
            -77.029428699999997, 
            38.925672400000003
        ], 
        "location": [
            "eurasia", 
            "reykjavik", 
            "jamaica", 
            "kingston", 
            "africa", 
            "pacific", 
            "united states", 
            "senegal", 
            "new zealand", 
            "canada", 
            "europe", 
            "dakar", 
            "washington d.c.", 
            "australia", 
            "iceland", 
            "belgium", 
            "brussels", 
            "toronto", 
            "east asia", 
            "wellington", 
            "melbourne", 
            "western hemisphere"
        ], 
        "digitized": true, 
        "timestamp": "2016-07-20T18:31:21.233000Z", 
        "campaigns": [], 
        "extract_timestamp": "2016-07-20T18:27:22.224000Z", 
        "date": "1990-05-30", 
        "shelf_id": "Spouse Series", 
        "other_title": [], 
        "dates": [
            "1990-05-30T00:00:00Z"
        ], 
        "language": [
            "english"
        ], 
        "url": "https://www.loc.gov/item/mfdipbib000673/", 
        "hassegments": false, 
        "image_url": [], 
        "aka": [
            "http://www.loc.gov/item/mfdipbib000673/", 
            "http://hdl.loc.gov/loc.mss/mfdip.2004lee01", 
            "http://www.loc.gov/resource/mfdip.2004lee01/", 
            "http://www.loc.gov/item/mfdip.2004lee01/"
        ]
    }, 
    {
        "access_restricted": false, 
        "original_format": [
            "manuscript/mixed material"
        ], 
        "contributor": [
            "fenzi, jewell", 
            "morin, ann miller"
        ], 
        "latlong": "48.8430555556,2.32138888889", 
        "id": "http://www.loc.gov/item/mfdipbib000836/", 
        "partof": [
            "manuscript division", 
            "frontline diplomacy: the foreign affairs oral history collection of the association for diplomatic studies and training", 
            "american memory"
        ], 
        "subject": [
            "association for diplomatic studies and training", 
            "diplomacy", 
            "foreign relations", 
            "oral history", 
            "spouses", 
            "interviews"
        ], 
        "index": 5, 
        "group": [
            "mfdip", 
            "foreign-affairs-oral-history"
        ], 
        "title": "Interview with Ann Miller Morin", 
        "coordinates": [
            "48.8430555556,2.32138888889"
        ], 
        "score": 3.5666291999999999, 
        "lonlat": [
            2.3213888888900001, 
            48.843055555600003
        ], 
        "location": [
            "washington d.c.", 
            "europe", 
            "algiers", 
            "east asia", 
            "algeria", 
            "eurasia", 
            "paris", 
            "le havre", 
            "pacific", 
            "france", 
            "united states", 
            "baghdad", 
            "western hemisphere", 
            "kobe", 
            "japan", 
            "iraq", 
            "near east"
        ], 
        "digitized": true, 
        "timestamp": "2016-07-20T18:32:05.602000Z", 
        "campaigns": [], 
        "extract_timestamp": "2016-07-20T18:27:27.142000Z", 
        "date": "1988-06-21", 
        "shelf_id": "Spouse Series", 
        "other_title": [], 
        "dates": [
            "1988-06-21T00:00:00Z"
        ], 
        "language": [
            "english"
        ], 
        "url": "https://www.loc.gov/item/mfdipbib000836/", 
        "hassegments": false, 
        "image_url": [], 
        "aka": [
            "http://www.loc.gov/item/mfdipbib000836/", 
            "http://hdl.loc.gov/loc.mss/mfdip.2004mor08", 
            "http://www.loc.gov/resource/mfdip.2004mor08/", 
            "http://www.loc.gov/item/mfdip.2004mor08/"
        ]
    }, 
    {
        "access_restricted": false, 
        "original_format": [
            "manuscript/mixed material"
        ], 
        "contributor": [
            "fenzi, jewell", 
            "squire, patricia cody"
        ], 
        "latlong": "38.9001118,-77.0163653", 
        "id": "http://www.loc.gov/item/mfdipbib001113/", 
        "partof": [
            "manuscript division", 
            "frontline diplomacy: the foreign affairs oral history collection of the association for diplomatic studies and training", 
            "american memory"
        ], 
        "subject": [
            "association for diplomatic studies and training", 
            "diplomacy", 
            "foreign relations", 
            "oral history", 
            "spouses", 
            "interviews"
        ], 
        "index": 6, 
        "group": [
            "mfdip", 
            "foreign-affairs-oral-history"
        ], 
        "title": "Interview with Patricia Cody Squire", 
        "coordinates": [
            "38.9001118,-77.0163653"
        ], 
        "score": 3.5648569999999999, 
        "lonlat": [
            -77.016365300000004, 
            38.900111799999998
        ], 
        "location": [
            "washington d.c.", 
            "europe", 
            "budapest", 
            "australia", 
            "leningrad", 
            "canberra", 
            "eurasia", 
            "czechoslovakia", 
            "washington", 
            "pacific", 
            "moscow", 
            "united states", 
            "ussr", 
            "western hemisphere", 
            "belgium", 
            "hungary", 
            "brussels", 
            "prague", 
            "east asia"
        ], 
        "digitized": true, 
        "timestamp": "2016-07-20T18:33:07.713000Z", 
        "campaigns": [], 
        "extract_timestamp": "2016-07-20T18:27:33.445000Z", 
        "date": "1990-04-30", 
        "shelf_id": "Spouse Series", 
        "other_title": [], 
        "dates": [
            "1990-04-30T00:00:00Z"
        ], 
        "language": [
            "english"
        ], 
        "url": "https://www.loc.gov/item/mfdipbib001113/", 
        "hassegments": false, 
        "image_url": [], 
        "aka": [
            "http://www.loc.gov/item/mfdipbib001113/", 
            "http://hdl.loc.gov/loc.mss/mfdip.2004squ02", 
            "http://www.loc.gov/resource/mfdip.2004squ02/", 
            "http://www.loc.gov/item/mfdip.2004squ02/"
        ]
    }
],
"item":{
    "source_collection": "The Foreign Affairs Oral History Collection of the Association for Diplomatic Studies and Training", 
    "display_offsite": true, 
    "contributors": [
        {
            "fenzi, jewell": "https://www.loc.gov/search/?fa=contributor%3Afenzi%2C+jewell&fo=json"
        }, 
        {
            "kidder, dorothy robinson": "https://www.loc.gov/search/?fa=contributor%3Akidder%2C+dorothy+robinson&fo=json"
        }
    ], 
    "access_restricted": false, 
    "site": [], 
    "original_format": [
        "manuscript/mixed material"
    ], 
    "genre": [
        "Interviews"
    ], 
    "latlong": "48.8430555556,2.32138888889", 
    "subject_headings": [
        "Association for Diplomatic Studies and Training", 
        "Diplomacy", 
        "Foreign relations", 
        "Oral history", 
        "Spouses", 
        "Interviews", 
        "France -- Paris", 
        "Vietnam -- Saigon", 
        "Brazil -- Rio de Janeiro", 
        "Thailand -- Bangkok", 
        "Australia -- Sydney", 
        "Canada -- Quebec -- Montreal", 
        "Europe and Eurasia", 
        "Western Hemisphere", 
        "East Asia and Pacific"
    ], 
    "created_published": [
        "June 1, 1998"
    ], 
    "extract_urls": [
        "http://hdl.loc.gov/loc.mss/mfdip.2004kid02#mfdip"
    ], 
    "id": "http://www.loc.gov/item/mfdipbib000609/", 
    "partof": [
        {
            "count": 1729, 
            "url": "https://www.loc.gov/collections/foreign-affairs-oral-history/?fo=json", 
            "title": "frontline diplomacy: the foreign affairs oral history collection of the association for diplomatic studies and training"
        }, 
        {
            "count": 139774, 
            "url": "https://www.loc.gov/search/?fa=partof%3Amanuscript+division&fo=json", 
            "title": "manuscript division"
        }, 
        {
            "count": 504295, 
            "url": "https://www.loc.gov/search/?fa=partof%3Aamerican+memory&fo=json", 
            "title": "american memory"
        }
    ], 
    "subject": [
        "association for diplomatic studies and training", 
        "diplomacy", 
        "foreign relations", 
        "oral history", 
        "spouses", 
        "interviews"
    ], 
    "index": 1, 
    "digital_id": [
        "http://hdl.loc.gov/loc.mss/mfdip.2004kid02"
    ], 
    "call_number": [
        "Spouse Series"
    ], 
    "group": [
        "mfdip", 
        "foreign-affairs-oral-history"
    ], 
    "score": 9.4985320000000009, 
    "title": "Interview with Dorothy Robinson Kidder ", 
    "coordinates": [
        "48.8430555556,2.32138888889"
    ], 
    "subjects": [
        {
            "association for diplomatic studies and training": "https://www.loc.gov/search/?fa=subject%3Aassociation+for+diplomatic+studies+and+training&fo=json"
        }, 
        {
            "diplomacy": "https://www.loc.gov/search/?fa=subject%3Adiplomacy&fo=json"
        }, 
        {
            "foreign relations": "https://www.loc.gov/search/?fa=subject%3Aforeign+relations&fo=json"
        }, 
        {
            "interviews": "https://www.loc.gov/search/?fa=subject%3Ainterviews&fo=json"
        }, 
        {
            "oral history": "https://www.loc.gov/search/?fa=subject%3Aoral+history&fo=json"
        }, 
        {
            "spouses": "https://www.loc.gov/search/?fa=subject%3Aspouses&fo=json"
        }
    ], 
    "lonlat": [
        2.3213888888900001, 
        48.843055555600003
    ], 
    "location": [
        {
            "australia": "https://www.loc.gov/search/?fa=location%3Aaustralia&fo=json"
        }, 
        {
            "bangkok": "https://www.loc.gov/search/?fa=location%3Abangkok&fo=json"
        }, 
        {
            "brazil": "https://www.loc.gov/search/?fa=location%3Abrazil&fo=json"
        }, 
        {
            "canada": "https://www.loc.gov/search/?fa=location%3Acanada&fo=json"
        }, 
        {
            "east asia": "https://www.loc.gov/search/?fa=location%3Aeast+asia&fo=json"
        }, 
        {
            "eurasia": "https://www.loc.gov/search/?fa=location%3Aeurasia&fo=json"
        }, 
        {
            "europe": "https://www.loc.gov/search/?fa=location%3Aeurope&fo=json"
        }, 
        {
            "france": "https://www.loc.gov/search/?fa=location%3Afrance&fo=json"
        }, 
        {
            "montreal": "https://www.loc.gov/search/?fa=location%3Amontreal&fo=json"
        }, 
        {
            "pacific": "https://www.loc.gov/search/?fa=location%3Apacific&fo=json"
        }, 
        {
            "paris": "https://www.loc.gov/search/?fa=location%3Aparis&fo=json"
        }, 
        {
            "quebec": "https://www.loc.gov/search/?fa=location%3Aquebec&fo=json"
        }, 
        {
            "rio de janeiro": "https://www.loc.gov/search/?fa=location%3Ario+de+janeiro&fo=json"
        }, 
        {
            "saigon": "https://www.loc.gov/search/?fa=location%3Asaigon&fo=json"
        }, 
        {
            "sydney": "https://www.loc.gov/search/?fa=location%3Asydney&fo=json"
        }, 
        {
            "thailand": "https://www.loc.gov/search/?fa=location%3Athailand&fo=json"
        }, 
        {
            "vietnam": "https://www.loc.gov/search/?fa=location%3Avietnam&fo=json"
        }, 
        {
            "western hemisphere": "https://www.loc.gov/search/?fa=location%3Awestern+hemisphere&fo=json"
        }
    ], 
    "_version_": 1540399543132094464, 
    "type": [
        "manuscript/mixed material"
    ], 
    "other_formats": [], 
    "digitized": true, 
    "medium": [], 
    "repository": "Manuscript Division", 
    "format": [
        {
            "manuscript/mixed material": "https://www.loc.gov/search/?fa=original_format%3Amanuscript%2Fmixed+material&fo=json"
        }
    ], 
    "timestamp": "2016-07-20T18:31:21.233000Z", 
    "campaigns": [], 
    "extract_timestamp": "2016-07-20T18:27:22.224000Z", 
    "date": "19980601", 
    "shelf_id": "Spouse Series", 
    "other_title": [], 
    "dates": [
        {
            "1998": "https://www.loc.gov/search/?dates=1998-1998&fo=json"
        }
    ], 
    "language": [
        {
            "english": "https://www.loc.gov/search/?fa=language%3Aenglish&fo=json"
        }
    ], 
    "rights": [
        "<p>The Library of Congress provides access to these materials for  educational  and research purposes and makes no warranty with regard to  their use for other  purposes. The written permission of the copyright  owners and/or holders of  other rights (such as publicity and/or privacy  rights) is required for  distribution, reproduction, or other use of  protected items beyond that allowed  by fair use or other statutory  exemptions. There may be content that is protected  as \"works for hire\"  (copyright held by the party that commissioned  the original work)  and/or under the copyright or neighboring-rights laws of  other  nations.\u00a0 Responsibility for  making an independent legal assessment of  an item and securing any necessary  permissions ultimately rests with  persons desiring to use the item. See <a href=\"/legal/\">Legal Notices</a> and <a href=\"/legal/#privacy_publicity\">Privacy and Publicity Rights</a> for additional information and restrictions.</p>\r\n<p>The Library of Congress would like to learn more about these  materials  and to hear from individuals or institutions having any  additional  information. Please contact us through our <a href=\"//www.loc.gov/rr/askalib/\">Ask A Librarian</a> service.</p>\r\n<h2>Preferred Citation</h2>\r\n<p>Researchers wishing to cite this collection should include the following  information: <br>\r\n\tFrontline Diplomacy, Manuscript Division, Library of Congress, Washington, D.C. </p>\r\n<h2>Permissions</h2>\r\n<p>Items included in this  collection with the permission of  rights holders are listed below. For further use or reproduction of  those items  contact the rightsholders listed.</p>\r\n<p>Interview of William  W. Lehfeldt by William Burr, April  29, 1987, made available here with  permission from  The  Foundation for  Iranian Studies, 4343 Montgomery Avenue, Suite 200, Bethesda, MD   20814.</p>\r\n<p>Interview  of John  S. Service by Rosemary Levinson, 1977,  made available here with permission from  The  Regional Oral History  Office, 486 The Bancroft Library, University of  California, Berkeley,  Berkeley, California 94720-6000.</p>\r\n<p>Oral  history interviews conducted by Mrs. Ann  Miller Morin  (below), made available here with permission from Mrs. Ann Miller   Morin, 3330  North Leisure World Blvd., Apt. 808, Silver Spring, MD  20906.</p>\r\n<ul>\r\n\t<li>Interview  of Anne Cox Chambers, October 23, 1985</li>\r\n\t<li>Interview of Jane Abell Coon, November 4, 1986</li>\r\n\t<li>Interview of Betty Crites Dillon, December 9, 1987</li>\r\n\t<li>Interview of Ruth Lewis Farkas, October 24, 1985</li>\r\n\t<li>Interview of Rosemary Lucas Ginn, October 28, 1997</li>\r\n\t<li>Interview of Constance Ray Harvey, 1988</li>\r\n\t<li>Interview of Mari-Luci Jaramillo, February 21, 1987</li>\r\n\t<li>Interview of Jeane Jordan Kirkpatrick, May 28, 1987</li>\r\n\t<li>Interview of Caroline Clendening Laise, May 8, 1985</li>\r\n\t<li>Interview of Claire Boothe Luce, September 19, 1986\u00a0\u00a0\u00a0 \u00a0\u00a0\u00a0\u00a0\u00a0\u00a0\u00a0\u00a0\u00a0\u00a0\u00a0 </li>\r\n\t<li>Interview of Mary Seymour Olmsted, June 25, 1985</li>\r\n\t<li>Interview of Nancy Ostrander, May 14, 1986</li>\r\n\t<li>Interview of Rozanne L. Ridgway, March 18, 1987</li>\r\n\t<li>Interview of Mabel Murphy Smythe, May 2, 1986</li>\r\n\t<li>Interview of Margaret Joy Tibbetts, May 28, 1985</li>\r\n\t<li>Interview of Melissa Foelsh Wells, March 27, 1984</li>\r\n\t<li>Interview       of Faith Ryan Whittlesey, December 7, 1988</li>\r\n</ul>\r\n<p>These 17 interviews are part of the collection on deposit in  the <a href=\"http://www.smith.edu/libraries/libs/ssc/\">Sophia Smith Collection <i class=\"icon icon-external-link\"><span>External</span></i></a>.</p>"
    ], 
    "url": "https://www.loc.gov/item/mfdipbib000609/", 
    "notes": [], 
    "hassegments": false, 
    "image_url": [], 
    "aka": [
        "http://www.loc.gov/item/mfdipbib000609/", 
        "http://hdl.loc.gov/loc.mss/mfdip.2004kid02", 
        "http://www.loc.gov/resource/mfdip.2004kid02/", 
        "http://www.loc.gov/item/mfdip.2004kid02/"
    ], 
    "contributor_names": [
        "Fenzi, Jewell (Interviewer)", 
        "Kidder, Dorothy Robinson (Interviewee)"
    ]
},
"type":"legacyzoom",
"options":{
    "all": null, 
    "partial": false, 
    "request_params": {
        "fo": "json"
    }, 
    "searchIn": null, 
    "site_id": null, 
    "operator": null, 
    "startIndex": 1, 
    "startPage": null, 
    "searchWithin": null, 
    "duration": 0.22970890998840332, 
    "default_count": 25, 
    "id": "mfdipbib000609/", 
    "index": null, 
    "style": null, 
    "site_type": null, 
    "searchType": null, 
    "callback": null, 
    "segments": null, 
    "facet_count": null, 
    "field": null, 
    "newSearch": null, 
    "sortOrder": null, 
    "template": "item/base", 
    "attribute": null, 
    "facetPrefix": null, 
    "scheme": "https, https", 
    "iiif": false, 
    "onsite": false, 
    "release_id": 44970, 
    "outputEncoding": "UTF-8", 
    "format": "json", 
    "searchTerms": "", 
    "facetLimits": "", 
    "referer": null, 
    "path_info": "/item/mfdipbib000609/", 
    "inputEncoding": "UTF-8", 
    "application_version": "$Revision: 44970 $", 
    "latlong": null, 
    "count": null, 
    "distance": null, 
    "dates": null, 
    "resource": null, 
    "language": "en", 
    "suggested": null, 
    "excludeTerms": null, 
    "host": "www.loc.gov", 
    "item": null, 
    "query_string": "fo=json", 
    "sortBy": null
},
"resources":[
    {
        "files": [], 
        "url": "https://www.loc.gov/resource/mfdip.2004kid02/", 
        "image": "", 
        "caption": "", 
        "fulltext_file": "http://cdn.loc.gov/service/mss/mfdip/2004/2004kid02/2004kid02.xml", 
        "pdf": "http://cdn.loc.gov/service/mss/mfdip/2004/2004kid02/2004kid02.pdf"
    }
]}